ibench/__init__.py
ibench/add_seqs.py
ibench/check_presence.py
ibench/config.py
ibench/constants.py
ibench/download_data.py
ibench/extract_hits.py
ibench/html_report.py
ibench/modify_db.py
ibench/performance.py
ibench/query_table.py
ibench/run.py
ibench/utils.py
ibench/validate_assignments.py
ibench/input/__init__.py
ibench/input/inspire.py
ibench/input/invitrospi.py
ibench/input/mascot.py
ibench/input/maxquant.py
ibench/input/mgf.py
ibench/input/mzml.py
ibench/input/peaks.py
ibench/input/percolator.py
ibench/input/search_results.py
ibench-2.0.dist-info/LICENSE
ibench-2.0.dist-info/METADATA
ibench-2.0.dist-info/WHEEL
ibench-2.0.dist-info/entry_points.txt
ibench-2.0.dist-info/top_level.txt
ibench-2.0.dist-info/RECORD
