Metadata-Version: 2.1
Name: ibench
Version: 2.0
Summary: Benchmarking for mass spectrometry identifications.
Author: John Cormican, Juliane Liepe
Author-email: juliane.liepe@mpinat.mpg.de
Project-URL: Homepage, https://github.com/QuantSysBio/iBench
Project-URL: Tracker, https://github.com/QuantSysBio/iBench/issues
Requires-Python: >=3.8
License-File: LICENSE
Requires-Dist: biopython (==1.79)
Requires-Dist: certifi (==2022.12.7)
Requires-Dist: lxml (==4.9.1)
Requires-Dist: numpy (==1.19.5)
Requires-Dist: pandas (==1.4.3)
Requires-Dist: plotly (==5.10.0)
Requires-Dist: pyopenms (==2.6.0)
Requires-Dist: pyteomics (==4.5.4)
Requires-Dist: python-dateutil (==2.8.2)
Requires-Dist: pytz (==2022.2.1)
Requires-Dist: PyYAML (==6.0)
Requires-Dist: six (==1.15.0)
Requires-Dist: tenacity (==8.0.1)
